{
  "@context": "/contexts/Card",
  "@id": "/cards/ALT_DUSTER_B_BR_65_C",
  "@type": "Card",
  "loreEntries": [
    {
      "@id": "/lore_entries/6NPTJ1HNY799BSFBN14NATQFCS",
      "@type": "LoreEntry",
      "loreEntryElements": [
        {
          "@id": "/lore_entry_elements/01K3R4K79N9AJF62T0JJYV4BFS",
          "@type": "LoreEntryElement",
          "loreEntryElementType": {
            "@id": "/lore_entry_element_types/01GR6AENPX6HQP8G16KNV7BNA2",
            "@type": "LoreEntryElementType",
            "id": "01GR6AENPX6HQP8G16KNV7BNA2",
            "reference": "FLAVOR_TEXT",
            "subject": "Flavor Text"
          },
          "id": "01K3R4K79N9AJF62T0JJYV4BFS",
          "text": "La haine est une lance tournée vers son propre cœur."
        },
        {
          "@id": "/lore_entry_elements/01K3R4K7AGQ0CKGBGXR3SVVA7D",
          "@type": "LoreEntryElement",
          "loreEntryElementType": {
            "@id": "/lore_entry_element_types/01GR6AE2ZSVVYP6SDJXN8Q5DVF",
            "@type": "LoreEntryElementType",
            "id": "01GR6AE2ZSVVYP6SDJXN8Q5DVF",
            "reference": "STORY",
            "subject": "Histoire"
          },
          "id": "01K3R4K7AGQ0CKGBGXR3SVVA7D",
          "text": ""
        },
        {
          "@id": "/lore_entry_elements/01K3R4K79ZNA44G15P2X454M7G",
          "@type": "LoreEntryElement",
          "loreEntryElementType": {
            "@id": "/lore_entry_element_types/01GR6AFCC93PF6T4EYVTXXYJY9",
            "@type": "LoreEntryElementType",
            "id": "01GR6AFCC93PF6T4EYVTXXYJY9",
            "reference": "INSPIRATION",
            "subject": "Inspiration"
          },
          "id": "01K3R4K79ZNA44G15P2X454M7G",
          "text": ""
        },
        {
          "@id": "/lore_entry_elements/01K3R4K7808RMKYNX327XDVS2Z",
          "@type": "LoreEntryElement",
          "loreEntryElementType": {
            "@id": "/lore_entry_element_types/01H19024M31D80P12EJCYX9GB0",
            "@type": "LoreEntryElementType",
            "id": "01H19024M31D80P12EJCYX9GB0",
            "reference": "NARRATOR",
            "subject": "Narré par"
          },
          "id": "01K3R4K7808RMKYNX327XDVS2Z",
          "text": ""
        },
        {
          "@id": "/lore_entry_elements/01K3R4K78A00Y9FQ2J7Q96GKQ0",
          "@type": "LoreEntryElement",
          "loreEntryElementType": {
            "@id": "/lore_entry_element_types/01GS7V4ZMD4F2Q0EVQ2GSSJHE2",
            "@type": "LoreEntryElementType",
            "id": "01GS7V4ZMD4F2Q0EVQ2GSSJHE2",
            "reference": "DATE",
            "subject": "Date"
          },
          "id": "01K3R4K78A00Y9FQ2J7Q96GKQ0",
          "text": ""
        }
      ],
      "loreEntryType": {
        "@id": "/lore_entry_types/01HNE2ZDSBVNHKJ8P47G3GACVQ",
        "@type": "LoreEntryType",
        "id": "01HNE2ZDSBVNHKJ8P47G3GACVQ",
        "reference": "HERO",
        "name": "Hero",
        "description": ""
      },
      "id": "6NPTJ1HNY799BSFBN14NATQFCS",
      "reference": "ALT_DUSTER_B_BR_65_C"
    }
  ],
  "cardType": {
    "@id": "/card_types/01GE7AC9WGQTNRP28T63FH8TZD",
    "@type": "CardType",
    "reference": "HERO",
    "id": "01GE7AC9WGQTNRP28T63FH8TZD",
    "name": "Héros"
  },
  "cardSubTypes": [],
  "cardSet": {
    "@id": "/card_sets/DUSTER",
    "@type": "CardSet",
    "id": "01K56FXHFTGF3DQ8XE8Q8Y5JG8",
    "reference": "DUSTER",
    "name": "Les Graines de l'Unité"
  },
  "rarity": {
    "@type": "Rarity",
    "@id": "/.well-known/genid/73a7590a67715eec1aaa",
    "reference": "COMMON",
    "id": "01GE7AC9WEQKW1Y1BF8SCY745A",
    "name": "Commun"
  },
  "cardRulings": [],
  "imagePath": "https://altered-prod-eu.s3.amazonaws.com/Art/DUSTER/CARDS/ALT_DUSTER_B_BR_65/JPG/fr_FR/c0dd7667f2f5c31bceef813676627a73.jpg",
  "assets": [],
  "lowerPrice": 0,
  "qrUrlDetail": "https://qr.altered.gg/ALT_DUSTER_B_BR_65_C",
  "reference": "ALT_DUSTER_B_BR_65_C",
  "id": "01JZJF4N7VS72BZZ89SKSF3XEN",
  "mainFaction": {
    "@id": "/factions/BR",
    "@type": "Faction",
    "reference": "BR",
    "color": "#c32637",
    "id": "01GE7AC9WY6PK56RADXXD6P1T4",
    "name": "Bravos"
  },
  "allImagePath": {
    "es-es": "",
    "en-us": "https://altered-prod-eu.s3.amazonaws.com/Art/DUSTER/CARDS/ALT_DUSTER_B_BR_65/JPG/en_US/1d0b1eca59b2d1f13be8a070ac072808.jpg",
    "it-it": "",
    "de-de": "",
    "fr-fr": "https://altered-prod-eu.s3.amazonaws.com/Art/DUSTER/CARDS/ALT_DUSTER_B_BR_65/JPG/fr_FR/c0dd7667f2f5c31bceef813676627a73.jpg"
  },
  "name": "Sol & Halua",
  "elements": {
    "MAIN_COST": "0",
    "RECALL_COST": "0",
    "PERMANENT": "2",
    "RESERVE": "2",
    "MAIN_EFFECT": "Lorsque vous passez en premier — Je gagne 1 compteur Quête. Puis, si j'ai au moins 3 compteurs Quête, créez un jeton Compagnon Léviathan [2/2/2 Halua] dans votre Expédition Compagnon. (Il a « Si votre Héros a au moins 5 compteurs Quête, je suis Gigantesque. »)"
  },
  "isSuspended": false,
  "isErrated": false,
  "isBanned": false,
  "collectorNumber": "SDU-019-H-FR"
}