{
  "@context": "/contexts/Card",
  "@id": "/cards/ALT_DUSTER_B_AX_96_R2",
  "@type": "Card",
  "loreEntries": [
    {
      "@id": "/lore_entries/4ENAW7H84V8EJS1GXH2HSAC2EN",
      "@type": "LoreEntry",
      "loreEntryElements": [
        {
          "@id": "/lore_entry_elements/01JZ37ZJFR75GPPNQKSZCJY12B",
          "@type": "LoreEntryElement",
          "loreEntryElementType": {
            "@id": "/lore_entry_element_types/01GR6AENPX6HQP8G16KNV7BNA2",
            "@type": "LoreEntryElementType",
            "id": "01GR6AENPX6HQP8G16KNV7BNA2",
            "reference": "FLAVOR_TEXT",
            "subject": "Flavor Text"
          },
          "id": "01JZ37ZJFR75GPPNQKSZCJY12B",
          "text": "\"È questo involucro fisico a definire chi sono?\""
        },
        {
          "@id": "/lore_entry_elements/01JZ37ZJGBKM5B9DMFFGMMW1KB",
          "@type": "LoreEntryElement",
          "loreEntryElementType": {
            "@id": "/lore_entry_element_types/01GR6AE2ZSVVYP6SDJXN8Q5DVF",
            "@type": "LoreEntryElementType",
            "id": "01GR6AE2ZSVVYP6SDJXN8Q5DVF",
            "reference": "STORY",
            "subject": "Story"
          },
          "id": "01JZ37ZJGBKM5B9DMFFGMMW1KB",
          "text": ""
        },
        {
          "@id": "/lore_entry_elements/01JZ37ZJG1BJA4YCTTZV1GDAKZ",
          "@type": "LoreEntryElement",
          "loreEntryElementType": {
            "@id": "/lore_entry_element_types/01GR6AFCC93PF6T4EYVTXXYJY9",
            "@type": "LoreEntryElementType",
            "id": "01GR6AFCC93PF6T4EYVTXXYJY9",
            "reference": "INSPIRATION",
            "subject": "Inspiration"
          },
          "id": "01JZ37ZJG1BJA4YCTTZV1GDAKZ",
          "text": ""
        },
        {
          "@id": "/lore_entry_elements/01JZ37ZJF5MNWDQXWAG300MXQR",
          "@type": "LoreEntryElement",
          "loreEntryElementType": {
            "@id": "/lore_entry_element_types/01H19024M31D80P12EJCYX9GB0",
            "@type": "LoreEntryElementType",
            "id": "01H19024M31D80P12EJCYX9GB0",
            "reference": "NARRATOR",
            "subject": "Narrator"
          },
          "id": "01JZ37ZJF5MNWDQXWAG300MXQR",
          "text": ""
        },
        {
          "@id": "/lore_entry_elements/01JZ37ZJFEN7SGJJ85DDZPWR7F",
          "@type": "LoreEntryElement",
          "loreEntryElementType": {
            "@id": "/lore_entry_element_types/01GS7V4ZMD4F2Q0EVQ2GSSJHE2",
            "@type": "LoreEntryElementType",
            "id": "01GS7V4ZMD4F2Q0EVQ2GSSJHE2",
            "reference": "DATE",
            "subject": "Date"
          },
          "id": "01JZ37ZJFEN7SGJJ85DDZPWR7F",
          "text": ""
        }
      ],
      "loreEntryType": {
        "@id": "/lore_entry_types/01HNGY4YPR0FVZVYWD8YFE0PHP",
        "@type": "LoreEntryType",
        "id": "01HNGY4YPR0FVZVYWD8YFE0PHP",
        "reference": "CHARACTER",
        "name": "Character",
        "description": ""
      },
      "id": "4ENAW7H84V8EJS1GXH2HSAC2EN",
      "reference": "ALT_DUSTER_B_AX_96_C"
    }
  ],
  "cardType": {
    "@id": "/card_types/01H19NWA92A4ERAC4ATMSZNASS",
    "@type": "CardType",
    "reference": "CHARACTER",
    "id": "01H19NWA92A4ERAC4ATMSZNASS",
    "name": "Personaggio"
  },
  "cardSubTypes": [
    {
      "@type": "CardSubType",
      "@id": "/.well-known/genid/2ec9db541c8e2bd5ee2d",
      "reference": "ROBOT",
      "id": "01HKAGPDNDJM76PRKTBB98Q0ZM",
      "name": "Robot"
    }
  ],
  "cardSet": {
    "@id": "/card_sets/DUSTER",
    "@type": "CardSet",
    "id": "01K56FXHFTGF3DQ8XE8Q8Y5JG8",
    "reference": "DUSTER",
    "name": "Semi di Unità"
  },
  "rarity": {
    "@type": "Rarity",
    "@id": "/.well-known/genid/1aafb20a25d70e1bd733",
    "reference": "RARE",
    "id": "01GE7AC9WY6PK56RADXXD6P1T5",
    "name": "Rare"
  },
  "cardRulings": [],
  "assets": [],
  "lowerPrice": 0,
  "qrUrlDetail": "https://qr.altered.gg/ALT_DUSTER_B_AX_96_R2",
  "reference": "ALT_DUSTER_B_AX_96_R2",
  "id": "01JYP9SVP8T70303X747EJ7SP8",
  "mainFaction": {
    "@id": "/factions/BR",
    "@type": "Faction",
    "reference": "BR",
    "color": "#c32637",
    "id": "01GE7AC9WY6PK56RADXXD6P1T4",
    "name": "Bravos"
  },
  "allImagePath": {
    "en-us": "https://altered-prod-eu.s3.amazonaws.com/Art/DUSTER/CARDS/ALT_DUSTER_B_AX_96/JPG/en_US/f43be9986f1e93e8fbbf693c2c8fa635.jpg",
    "es-es": "",
    "it-it": "",
    "de-de": "",
    "fr-fr": "https://altered-prod-eu.s3.amazonaws.com/Art/DUSTER/CARDS/ALT_DUSTER_B_AX_96/JPG/fr_FR/047b4ff7a362e35c91fba3ae1509a8cf.jpg"
  },
  "name": "Involucro",
  "elements": {
    "MAIN_COST": "#2#",
    "RECALL_COST": "3",
    "OCEAN_POWER": "1",
    "FOREST_POWER": "3",
    "MOUNTAIN_POWER": "3",
    "MAIN_EFFECT": "{R} Puoi mettere una carta dalla tua mano nella Riserva per pescare una carta."
  },
  "isSuspended": false,
  "isErrated": false,
  "isBanned": false,
  "collectorNumber": "SDU-009-F-IT"
}