{
  "@context": "/contexts/Card",
  "@id": "/cards/ALT_DUSTER_B_YZ_92_C",
  "@type": "Card",
  "loreEntries": [
    {
      "@id": "/lore_entries/5KMZS8X6TN9XSAVWWC3AEDQDDH",
      "@type": "LoreEntry",
      "loreEntryElements": [
        {
          "@id": "/lore_entry_elements/01JZ37ZWYBFZZ9XH3WKNYB1XQA",
          "@type": "LoreEntryElement",
          "loreEntryElementType": {
            "@id": "/lore_entry_element_types/01GR6AENPX6HQP8G16KNV7BNA2",
            "@type": "LoreEntryElementType",
            "id": "01GR6AENPX6HQP8G16KNV7BNA2",
            "reference": "FLAVOR_TEXT",
            "subject": "Flavor Text"
          },
          "id": "01JZ37ZWYBFZZ9XH3WKNYB1XQA",
          "text": "L'arte della sorpresa è presentarsi dove nessuno ti aspetta."
        },
        {
          "@id": "/lore_entry_elements/01JZ37ZX09SSSXEN6CF1Y65TQ7",
          "@type": "LoreEntryElement",
          "loreEntryElementType": {
            "@id": "/lore_entry_element_types/01GR6AE2ZSVVYP6SDJXN8Q5DVF",
            "@type": "LoreEntryElementType",
            "id": "01GR6AE2ZSVVYP6SDJXN8Q5DVF",
            "reference": "STORY",
            "subject": "Story"
          },
          "id": "01JZ37ZX09SSSXEN6CF1Y65TQ7",
          "text": ""
        },
        {
          "@id": "/lore_entry_elements/01JZ37ZWYYYZJ0J8HHFBDVPRT6",
          "@type": "LoreEntryElement",
          "loreEntryElementType": {
            "@id": "/lore_entry_element_types/01GR6AFCC93PF6T4EYVTXXYJY9",
            "@type": "LoreEntryElementType",
            "id": "01GR6AFCC93PF6T4EYVTXXYJY9",
            "reference": "INSPIRATION",
            "subject": "Inspiration"
          },
          "id": "01JZ37ZWYYYZJ0J8HHFBDVPRT6",
          "text": ""
        },
        {
          "@id": "/lore_entry_elements/01JZ37ZWWYAG4937D0TG3X4H3R",
          "@type": "LoreEntryElement",
          "loreEntryElementType": {
            "@id": "/lore_entry_element_types/01H19024M31D80P12EJCYX9GB0",
            "@type": "LoreEntryElementType",
            "id": "01H19024M31D80P12EJCYX9GB0",
            "reference": "NARRATOR",
            "subject": "Narrator"
          },
          "id": "01JZ37ZWWYAG4937D0TG3X4H3R",
          "text": ""
        },
        {
          "@id": "/lore_entry_elements/01JZ37ZWXRMRDVRHD6XVHD750G",
          "@type": "LoreEntryElement",
          "loreEntryElementType": {
            "@id": "/lore_entry_element_types/01GS7V4ZMD4F2Q0EVQ2GSSJHE2",
            "@type": "LoreEntryElementType",
            "id": "01GS7V4ZMD4F2Q0EVQ2GSSJHE2",
            "reference": "DATE",
            "subject": "Date"
          },
          "id": "01JZ37ZWXRMRDVRHD6XVHD750G",
          "text": ""
        }
      ],
      "loreEntryType": {
        "@id": "/lore_entry_types/01HNGY4YPR0FVZVYWD8YFE0PHP",
        "@type": "LoreEntryType",
        "id": "01HNGY4YPR0FVZVYWD8YFE0PHP",
        "reference": "CHARACTER",
        "name": "Character",
        "description": ""
      },
      "id": "5KMZS8X6TN9XSAVWWC3AEDQDDH",
      "reference": "ALT_DUSTER_B_YZ_92_C"
    }
  ],
  "cardType": {
    "@id": "/card_types/01H19NWA92A4ERAC4ATMSZNASS",
    "@type": "CardType",
    "reference": "CHARACTER",
    "id": "01H19NWA92A4ERAC4ATMSZNASS",
    "name": "Personaggio"
  },
  "cardSubTypes": [
    {
      "@type": "CardSubType",
      "@id": "/.well-known/genid/f70c0b663ceae79f2579",
      "reference": "SOLDIER",
      "id": "01HKAGQ5CZVEX15T5KTM40KQSA",
      "name": "Soldato"
    },
    {
      "@type": "CardSubType",
      "@id": "/.well-known/genid/4152fb6191a7cbdd7748",
      "reference": "ROGUE",
      "id": "01JZ2K0A1NZSGT69DP1WS2917B",
      "name": "Ribelle"
    }
  ],
  "cardSet": {
    "@id": "/card_sets/DUSTER",
    "@type": "CardSet",
    "id": "01K56FXHFTGF3DQ8XE8Q8Y5JG8",
    "reference": "DUSTER",
    "name": "Semi di Unità"
  },
  "rarity": {
    "@type": "Rarity",
    "@id": "/.well-known/genid/0ac431ed76a3320aaa3a",
    "reference": "COMMON",
    "id": "01GE7AC9WEQKW1Y1BF8SCY745A",
    "name": "Common"
  },
  "cardRulings": [],
  "assets": [],
  "lowerPrice": 0,
  "qrUrlDetail": "https://qr.altered.gg/ALT_DUSTER_B_YZ_92_C",
  "reference": "ALT_DUSTER_B_YZ_92_C",
  "id": "01JYP9SVQQ77MRBTN00YYV9NSW",
  "mainFaction": {
    "@id": "/factions/YZ",
    "@type": "Faction",
    "reference": "YZ",
    "color": "#764891",
    "id": "01GE7AC9WEQKW1Y1BF8SCY7459",
    "name": "Yzmir"
  },
  "allImagePath": {
    "es-es": "",
    "it-it": "",
    "de-de": "",
    "en-us": "https://altered-prod-eu.s3.amazonaws.com/Art/DUSTER/CARDS/ALT_DUSTER_B_YZ_92/JPG/en_US/0efecd1d8d309cf5a2c289ffff2636ce.jpg",
    "fr-fr": "https://altered-prod-eu.s3.amazonaws.com/Art/DUSTER/CARDS/ALT_DUSTER_B_YZ_92/JPG/fr_FR/8918567e318d9cbc62c794b983405add.jpg"
  },
  "name": "Mochizuki Chiyome",
  "elements": {
    "MAIN_COST": "3",
    "RECALL_COST": "3",
    "OCEAN_POWER": "3",
    "FOREST_POWER": "3",
    "MOUNTAIN_POWER": "3",
    "ECHO_EFFECT": "{D}: paga {1} in meno per il prossimo incantesimo che giochi in questo turno, fino a un minimo di {1}. (Scartami dalla Riserva per eseguire questa azione.)"
  },
  "isSuspended": false,
  "isErrated": false,
  "isBanned": false,
  "collectorNumber": "SDU-099-C-IT"
}