{
  "@context": "/contexts/Card",
  "@id": "/cards/ALT_DUSTER_B_AX_96_R1",
  "@type": "Card",
  "loreEntries": [
    {
      "@id": "/lore_entries/4ENAW7H84V8EJS1GXH2HSAC2EN",
      "@type": "LoreEntry",
      "loreEntryElements": [
        {
          "@id": "/lore_entry_elements/01JZ37ZJFR75GPPNQKSZCJY12B",
          "@type": "LoreEntryElement",
          "loreEntryElementType": {
            "@id": "/lore_entry_element_types/01GR6AENPX6HQP8G16KNV7BNA2",
            "@type": "LoreEntryElementType",
            "id": "01GR6AENPX6HQP8G16KNV7BNA2",
            "reference": "FLAVOR_TEXT",
            "subject": "Flavor Text"
          },
          "id": "01JZ37ZJFR75GPPNQKSZCJY12B",
          "text": "« Cette enveloppe me définit-elle ? »"
        },
        {
          "@id": "/lore_entry_elements/01JZ37ZJGBKM5B9DMFFGMMW1KB",
          "@type": "LoreEntryElement",
          "loreEntryElementType": {
            "@id": "/lore_entry_element_types/01GR6AE2ZSVVYP6SDJXN8Q5DVF",
            "@type": "LoreEntryElementType",
            "id": "01GR6AE2ZSVVYP6SDJXN8Q5DVF",
            "reference": "STORY",
            "subject": "Histoire"
          },
          "id": "01JZ37ZJGBKM5B9DMFFGMMW1KB",
          "text": ""
        },
        {
          "@id": "/lore_entry_elements/01JZ37ZJG1BJA4YCTTZV1GDAKZ",
          "@type": "LoreEntryElement",
          "loreEntryElementType": {
            "@id": "/lore_entry_element_types/01GR6AFCC93PF6T4EYVTXXYJY9",
            "@type": "LoreEntryElementType",
            "id": "01GR6AFCC93PF6T4EYVTXXYJY9",
            "reference": "INSPIRATION",
            "subject": "Inspiration"
          },
          "id": "01JZ37ZJG1BJA4YCTTZV1GDAKZ",
          "text": ""
        },
        {
          "@id": "/lore_entry_elements/01JZ37ZJF5MNWDQXWAG300MXQR",
          "@type": "LoreEntryElement",
          "loreEntryElementType": {
            "@id": "/lore_entry_element_types/01H19024M31D80P12EJCYX9GB0",
            "@type": "LoreEntryElementType",
            "id": "01H19024M31D80P12EJCYX9GB0",
            "reference": "NARRATOR",
            "subject": "Narré par"
          },
          "id": "01JZ37ZJF5MNWDQXWAG300MXQR",
          "text": ""
        },
        {
          "@id": "/lore_entry_elements/01JZ37ZJFEN7SGJJ85DDZPWR7F",
          "@type": "LoreEntryElement",
          "loreEntryElementType": {
            "@id": "/lore_entry_element_types/01GS7V4ZMD4F2Q0EVQ2GSSJHE2",
            "@type": "LoreEntryElementType",
            "id": "01GS7V4ZMD4F2Q0EVQ2GSSJHE2",
            "reference": "DATE",
            "subject": "Date"
          },
          "id": "01JZ37ZJFEN7SGJJ85DDZPWR7F",
          "text": ""
        }
      ],
      "loreEntryType": {
        "@id": "/lore_entry_types/01HNGY4YPR0FVZVYWD8YFE0PHP",
        "@type": "LoreEntryType",
        "id": "01HNGY4YPR0FVZVYWD8YFE0PHP",
        "reference": "CHARACTER",
        "name": "Character",
        "description": ""
      },
      "id": "4ENAW7H84V8EJS1GXH2HSAC2EN",
      "reference": "ALT_DUSTER_B_AX_96_C"
    }
  ],
  "cardType": {
    "@id": "/card_types/01H19NWA92A4ERAC4ATMSZNASS",
    "@type": "CardType",
    "reference": "CHARACTER",
    "id": "01H19NWA92A4ERAC4ATMSZNASS",
    "name": "Personnage"
  },
  "cardSubTypes": [
    {
      "@type": "CardSubType",
      "@id": "/.well-known/genid/9ee7cfe0300aaf38f289",
      "reference": "ROBOT",
      "id": "01HKAGPDNDJM76PRKTBB98Q0ZM",
      "name": "Robot"
    }
  ],
  "cardSet": {
    "@id": "/card_sets/DUSTER",
    "@type": "CardSet",
    "id": "01K56FXHFTGF3DQ8XE8Q8Y5JG8",
    "reference": "DUSTER",
    "name": "Les Graines de l'Unité"
  },
  "rarity": {
    "@type": "Rarity",
    "@id": "/.well-known/genid/cd1c21b0d0e8822320b3",
    "reference": "RARE",
    "id": "01GE7AC9WY6PK56RADXXD6P1T5",
    "name": "Rare"
  },
  "cardRulings": [],
  "imagePath": "https://altered-prod-eu.s3.amazonaws.com/Art/DUSTER/CARDS/ALT_DUSTER_B_AX_96/JPG/fr_FR/2eb2b4147076ab578c2be6f3f6c7f88b.jpg",
  "assets": [],
  "lowerPrice": 0,
  "qrUrlDetail": "https://qr.altered.gg/ALT_DUSTER_B_AX_96_R1",
  "reference": "ALT_DUSTER_B_AX_96_R1",
  "id": "01JYP9SVP8T70303X747EJ7SP5",
  "mainFaction": {
    "@id": "/factions/AX",
    "@type": "Faction",
    "reference": "AX",
    "color": "#8c432a",
    "id": "01GE7AC9XBG707G19F03A95TH1",
    "name": "Axiom"
  },
  "allImagePath": {
    "de-de": "",
    "it-it": "",
    "en-us": "https://altered-prod-eu.s3.amazonaws.com/Art/DUSTER/CARDS/ALT_DUSTER_B_AX_96/JPG/en_US/f238f26f7a361bb8142b68a80af1e0ae.jpg",
    "es-es": "",
    "fr-fr": "https://altered-prod-eu.s3.amazonaws.com/Art/DUSTER/CARDS/ALT_DUSTER_B_AX_96/JPG/fr_FR/2eb2b4147076ab578c2be6f3f6c7f88b.jpg"
  },
  "name": "L'Hôte",
  "elements": {
    "MAIN_COST": "#2#",
    "RECALL_COST": "3",
    "OCEAN_POWER": "1",
    "FOREST_POWER": "3",
    "MOUNTAIN_POWER": "3",
    "MAIN_EFFECT": "{R} Vous pouvez mettre une carte de votre main en Réserve pour piocher une carte."
  },
  "isSuspended": false,
  "isErrated": false,
  "isBanned": false,
  "collectorNumber": "SDU-009-R-FR"
}